[
  {
    "name": "Rusty Broadsword",
    "icon": "sword2.png",
    "prestige": 0,
    "slot": "mainHand",
    "rarity": "common",
    "classRestriction": "warrior",
    "noDrop": false,
    "hpRaw": 0,
    "manaRaw": 0,
    "dps": 3,
    "armor": 0,
    "stamina": 0,
    "defense": 0,
    "intelligence": 0,
    "strength": 0,
    "accuracy": 0
  },
  {
    "name": "Rusty Knife",
    "icon": "dagger1.png",
    "prestige": 0,
    "slot": "mainHand",
    "rarity": "common",
    "classRestriction": "ANY",
    "noDrop": false,
    "hpRaw": 0,
    "manaRaw": 0,
    "dps": 1,
    "armor": 0,
    "stamina": 0,
    "defense": 0,
    "intelligence": 0,
    "strength": 0,
    "accuracy": 0
  },
  {
    "name": "Rusty Old Shield",
    "icon": "shield1.png",
    "prestige": 0,
    "slot": "mainHand",
    "rarity": "common",
    "classRestriction": "warrior",
    "noDrop": false,
    "hpRaw": 0,
    "manaRaw": 0,
    "dps": 0,
    "armor": 2,
    "stamina": 0,
    "defense": 1,
    "intelligence": 0,
    "strength": 0,
    "accuracy": 0
  },
  {
    "name": "Cracked Staff",
    "icon": "crackedstaff.png",
    "prestige": 0,
    "slot": "mainHand",
    "rarity": "common",
    "classRestriction": "wizard",
    "noDrop": false,
    "hpRaw": 0,
    "manaRaw": 2,
    "dps": 0,
    "armor": 0,
    "stamina": 0,
    "defense": 0,
    "intelligence": 0,
    "strength": 0,
    "accuracy": 0
  },
  {
    "name": "Chainmail Vest",
    "icon": "chest_chainmail1.png",
    "prestige": 0,
    "slot": "chest",
    "rarity": "common",
    "classRestriction": "rogue",
    "noDrop": false,
    "hpRaw": 0,
    "manaRaw": 0,
    "dps": 0,
    "armor": 3,
    "stamina": 0,
    "defense": 0,
    "intelligence": 0,
    "strength": 0,
    "accuracy": 0
  },
  {
    "name": "Chainmail Leggings",
    "icon": "legs_chainmail1.png",
    "prestige": 0,
    "slot": "legs",
    "rarity": "common",
    "classRestriction": "rogue",
    "noDrop": false,
    "hpRaw": 0,
    "manaRaw": 0,
    "dps": 0,
    "armor": 3,
    "stamina": 0,
    "defense": 0,
    "intelligence": 0,
    "strength": 0,
    "accuracy": 0
  },
  {
    "name": "Chainmail Boots",
    "icon": "feet_chainmail1.png",
    "prestige": 0,
    "slot": "feet",
    "rarity": "common",
    "classRestriction": "rogue",
    "noDrop": false,
    "hpRaw": 0,
    "manaRaw": 0,
    "dps": 0,
    "armor": 3,
    "stamina": 0,
    "defense": 0,
    "intelligence": 0,
    "strength": 0,
    "accuracy": 0
  },
  {
    "name": "Chainmail Coif",
    "icon": "head_chainmail1.png",
    "prestige": 0,
    "slot": "head",
    "rarity": "common",
    "classRestriction": "rogue",
    "noDrop": false,
    "hpRaw": 0,
    "manaRaw": 0,
    "dps": 0,
    "armor": 2,
    "stamina": 0,
    "defense": 0,
    "intelligence": 0,
    "strength": 0,
    "accuracy": 0
  },
  {
    "name": "Simple Ring",
    "icon": "ring1.png",
    "prestige": 0,
    "slot": "jewelry",
    "rarity": "common",
    "classRestriction": "ANY",
    "noDrop": false,
    "hpRaw": 2,
    "manaRaw": 2,
    "dps": 0,
    "armor": 0,
    "stamina": 0,
    "defense": 0,
    "intelligence": 0,
    "strength": 0,
    "accuracy": 0
  },
  {
    "name": "Simple Earring",
    "icon": "earring1.png",
    "prestige": 0,
    "slot": "jewelry",
    "rarity": "common",
    "classRestriction": "ANY",
    "noDrop": false,
    "hpRaw": 0,
    "manaRaw": 0,
    "dps": 0,
    "armor": 0,
    "stamina": 0,
    "defense": 0,
    "intelligence": 1,
    "strength": 0,
    "accuracy": 0
  },
  {
    "name": "Basic Bow",
    "icon": "bow1.png",
    "prestige": 0,
    "slot": "mainHand",
    "rarity": "common",
    "classRestriction": "ranger",
    "noDrop": false,
    "hpRaw": 0,
    "manaRaw": 0,
    "dps": 3,
    "armor": 0,
    "stamina": 0,
    "defense": 0,
    "intelligence": 0,
    "strength": 0,
    "accuracy": 0
  },
  {
    "name": "Cloth Shirt",
    "icon": "chest_cloth1.png",
    "prestige": 0,
    "slot": "chest",
    "rarity": "common",
    "classRestriction": "ANY",
    "noDrop": false,
    "hpRaw": 0,
    "manaRaw": 0,
    "dps": 0,
    "armor": 1,
    "stamina": 0,
    "defense": 0,
    "intelligence": 0,
    "strength": 0,
    "accuracy": 0
  },
  {
    "name": "Cloth Pants",
    "icon": "legs_cloth1.png",
    "prestige": 0,
    "slot": "legs",
    "rarity": "common",
    "classRestriction": "ANY",
    "noDrop": false,
    "hpRaw": 0,
    "manaRaw": 0,
    "dps": 0,
    "armor": 1,
    "stamina": 0,
    "defense": 0,
    "intelligence": 0,
    "strength": 0,
    "accuracy": 0
  },
  {
    "name": "Shabby Robe",
    "icon": "robe2.png",
    "prestige": 0,
    "slot": "chest",
    "rarity": "common",
    "classRestriction": "wizard",
    "noDrop": false,
    "hpRaw": 0,
    "manaRaw": 5,
    "dps": 0,
    "armor": 2,
    "stamina": 0,
    "defense": 0,
    "intelligence": 0,
    "strength": 0,
    "accuracy": 0
  },
  {
    "name": "Simple Grey Robe",
    "icon": "robe5.png",
    "prestige": 0,
    "slot": "chest",
    "rarity": "common",
    "classRestriction": "wizard",
    "noDrop": false,
    "hpRaw": 0,
    "manaRaw": 0,
    "dps": 0,
    "armor": 2,
    "stamina": 0,
    "defense": 0,
    "intelligence": 5,
    "strength": 0,
    "accuracy": 0
  },
  {
    "name": "Blue Cotton Robe",
    "icon": "robe1.png",
    "prestige": 0,
    "slot": "chest",
    "rarity": "common",
    "classRestriction": "wizard",
    "noDrop": false,
    "hpRaw": 5,
    "manaRaw": 5,
    "dps": 0,
    "armor": 3,
    "stamina": 0,
    "defense": 0,
    "intelligence": 2,
    "strength": 0,
    "accuracy": 0
  },
  {
    "name": "Sparkling Metallic Robe",
    "icon": "robe3.png",
    "prestige": 5,
    "slot": "chest",
    "rarity": "uncommon",
    "classRestriction": "wizard",
    "noDrop": true,
    "hpRaw": 25,
    "manaRaw": 50,
    "dps": 0,
    "armor": 10,
    "stamina": 2,
    "defense": 0,
    "intelligence": 10,
    "strength": 0,
    "accuracy": 0
  },
  {
    "name": "Robe of Eternity",
    "icon": "robe4.png",
    "prestige": 10,
    "slot": "chest",
    "rarity": "epic",
    "classRestriction": "wizard",
    "noDrop": true,
    "hpRaw": 50,
    "manaRaw": 100,
    "dps": 0,
    "armor": 15,
    "stamina": 5,
    "defense": 5,
    "intelligence": 25,
    "strength": 0,
    "accuracy": 5
  },
  {
    "name": "Tzip's Crooked Dagger",
    "icon": "dagger2.png",
    "prestige": 5,
    "slot": "mainHand",
    "rarity": "rare",
    "classRestriction": "rogue",
    "noDrop": true,
    "hpRaw": 25,
    "manaRaw": 0,
    "dps": 15,
    "armor": 0,
    "stamina": 3,
    "defense": 3,
    "intelligence": 0,
    "strength": 5,
    "accuracy": 3
  }
]